de.upb.soot.basic.controlStatements.ControlStatements.<init>()V{
invokespecial < Source, Ljava/lang/Object, <init>()V > 1 @0 exception:3	invokespecial < Source, Ljava/lang/Object, <init>()V > v1 @0 exception:v3
																							com.ibm.wala.cast.java.ssa.AstJavaInvokeInstruction
}

de.upb.soot.basic.controlStatements.ControlStatements.tableSwitch(I)V{
switch 2 [0->3,1->4,2->5,3->6,4->7]	switch v2 [0->3,1->4,2->5,3->6,4->7]
																							com.ibm.wala.ssa.SSASwitchInstruction
goto (from iindex= 1 to iindex = 12)	goto (from iindex= 1 to iindex = 12)
																							com.ibm.wala.ssa.SSAGotoInstruction
10 = getstatic < Source, Ljava/lang/System, out, <Source,Ljava/io/PrintStream> >	v10 = getstatic < Source, Ljava/lang/System, out, <Source,Ljava/io/PrintStream> >
																							com.ibm.wala.classLoader.JavaLanguage$JavaInstructionFactory$7
invokevirtual < Source, Ljava/io/PrintStream, println(Ljava/lang/String;)V > 10,11 @3 exception:12	invokevirtual < Source, Ljava/io/PrintStream, println(Ljava/lang/String;)V > v10,v11 @3 exception:v12
																							com.ibm.wala.cast.java.ssa.AstJavaInvokeInstruction
14 = getstatic < Source, Ljava/lang/System, out, <Source,Ljava/io/PrintStream> >	v14 = getstatic < Source, Ljava/lang/System, out, <Source,Ljava/io/PrintStream> >
																							com.ibm.wala.classLoader.JavaLanguage$JavaInstructionFactory$7
invokevirtual < Source, Ljava/io/PrintStream, println(Ljava/lang/String;)V > 14,15 @5 exception:16	invokevirtual < Source, Ljava/io/PrintStream, println(Ljava/lang/String;)V > v14,v15 @5 exception:v16
																							com.ibm.wala.cast.java.ssa.AstJavaInvokeInstruction
18 = getstatic < Source, Ljava/lang/System, out, <Source,Ljava/io/PrintStream> >	v18 = getstatic < Source, Ljava/lang/System, out, <Source,Ljava/io/PrintStream> >
																							com.ibm.wala.classLoader.JavaLanguage$JavaInstructionFactory$7
invokevirtual < Source, Ljava/io/PrintStream, println(Ljava/lang/String;)V > 18,19 @7 exception:20	invokevirtual < Source, Ljava/io/PrintStream, println(Ljava/lang/String;)V > v18,v19 @7 exception:v20
																							com.ibm.wala.cast.java.ssa.AstJavaInvokeInstruction
22 = getstatic < Source, Ljava/lang/System, out, <Source,Ljava/io/PrintStream> >	v22 = getstatic < Source, Ljava/lang/System, out, <Source,Ljava/io/PrintStream> >
																							com.ibm.wala.classLoader.JavaLanguage$JavaInstructionFactory$7
invokevirtual < Source, Ljava/io/PrintStream, println(Ljava/lang/String;)V > 22,23 @9 exception:24	invokevirtual < Source, Ljava/io/PrintStream, println(Ljava/lang/String;)V > v22,v23 @9 exception:v24
																							com.ibm.wala.cast.java.ssa.AstJavaInvokeInstruction
26 = getstatic < Source, Ljava/lang/System, out, <Source,Ljava/io/PrintStream> >	v26 = getstatic < Source, Ljava/lang/System, out, <Source,Ljava/io/PrintStream> >
																							com.ibm.wala.classLoader.JavaLanguage$JavaInstructionFactory$7
invokevirtual < Source, Ljava/io/PrintStream, println(Ljava/lang/String;)V > 26,27 @11 exception:28	invokevirtual < Source, Ljava/io/PrintStream, println(Ljava/lang/String;)V > v26,v27 @11 exception:v28
																							com.ibm.wala.cast.java.ssa.AstJavaInvokeInstruction
30 = getstatic < Source, Ljava/lang/System, out, <Source,Ljava/io/PrintStream> >	v30 = getstatic < Source, Ljava/lang/System, out, <Source,Ljava/io/PrintStream> >
																							com.ibm.wala.classLoader.JavaLanguage$JavaInstructionFactory$7
invokevirtual < Source, Ljava/io/PrintStream, println(Ljava/lang/String;)V > 30,31 @13 exception:32	invokevirtual < Source, Ljava/io/PrintStream, println(Ljava/lang/String;)V > v30,v31 @13 exception:v32
																							com.ibm.wala.cast.java.ssa.AstJavaInvokeInstruction
}

de.upb.soot.basic.controlStatements.ControlStatements.simpleSwitchBreak(III)V{
switch 2 [10->3,20->5]	switch v2 [10->3,20->5]
																							com.ibm.wala.ssa.SSASwitchInstruction
goto (from iindex= 1 to iindex = 14)	goto (from iindex= 1 to iindex = 14)
																							com.ibm.wala.ssa.SSAGotoInstruction
9 = getstatic < Source, Ljava/lang/System, out, <Source,Ljava/io/PrintStream> >	v9 = getstatic < Source, Ljava/lang/System, out, <Source,Ljava/io/PrintStream> >
																							com.ibm.wala.classLoader.JavaLanguage$JavaInstructionFactory$7
12 = binaryop(add) 13 , 2	v12 = binaryop(add) v13 , v2
																							com.ibm.wala.classLoader.JavaLanguage$JavaInstructionFactory$4
11 = binaryop(add) 12 , 14	v11 = binaryop(add) v12 , v14
																							com.ibm.wala.classLoader.JavaLanguage$JavaInstructionFactory$4
10 = binaryop(add) 11 , 3	v10 = binaryop(add) v11 , v3
																							com.ibm.wala.classLoader.JavaLanguage$JavaInstructionFactory$4
invokevirtual < Source, Ljava/io/PrintStream, println(Ljava/lang/String;)V > 9,10 @6 exception:15	invokevirtual < Source, Ljava/io/PrintStream, println(Ljava/lang/String;)V > v9,v10 @6 exception:v15
																							com.ibm.wala.cast.java.ssa.AstJavaInvokeInstruction
goto (from iindex= 7 to iindex = -1)	goto (from iindex= 7 to iindex = -1)
																							com.ibm.wala.ssa.SSAGotoInstruction
17 = getstatic < Source, Ljava/lang/System, out, <Source,Ljava/io/PrintStream> >	v17 = getstatic < Source, Ljava/lang/System, out, <Source,Ljava/io/PrintStream> >
																							com.ibm.wala.classLoader.JavaLanguage$JavaInstructionFactory$7
20 = binaryop(add) 13 , 2	v20 = binaryop(add) v13 , v2
																							com.ibm.wala.classLoader.JavaLanguage$JavaInstructionFactory$4
19 = binaryop(add) 20 , 21	v19 = binaryop(add) v20 , v21
																							com.ibm.wala.classLoader.JavaLanguage$JavaInstructionFactory$4
18 = binaryop(add) 19 , 3	v18 = binaryop(add) v19 , v3
																							com.ibm.wala.classLoader.JavaLanguage$JavaInstructionFactory$4
invokevirtual < Source, Ljava/io/PrintStream, println(Ljava/lang/String;)V > 17,18 @12 exception:22	invokevirtual < Source, Ljava/io/PrintStream, println(Ljava/lang/String;)V > v17,v18 @12 exception:v22
																							com.ibm.wala.cast.java.ssa.AstJavaInvokeInstruction
goto (from iindex= 13 to iindex = -1)	goto (from iindex= 13 to iindex = -1)
																							com.ibm.wala.ssa.SSAGotoInstruction
25 = getstatic < Source, Ljava/lang/System, out, <Source,Ljava/io/PrintStream> >	v25 = getstatic < Source, Ljava/lang/System, out, <Source,Ljava/io/PrintStream> >
																							com.ibm.wala.classLoader.JavaLanguage$JavaInstructionFactory$7
28 = binaryop(add) 29 , 2	v28 = binaryop(add) v29 , v2
																							com.ibm.wala.classLoader.JavaLanguage$JavaInstructionFactory$4
27 = binaryop(add) 28 , 14	v27 = binaryop(add) v28 , v14
																							com.ibm.wala.classLoader.JavaLanguage$JavaInstructionFactory$4
26 = binaryop(add) 27 , 3	v26 = binaryop(add) v27 , v3
																							com.ibm.wala.classLoader.JavaLanguage$JavaInstructionFactory$4
invokevirtual < Source, Ljava/io/PrintStream, println(Ljava/lang/String;)V > 25,26 @18 exception:30	invokevirtual < Source, Ljava/io/PrintStream, println(Ljava/lang/String;)V > v25,v26 @18 exception:v30
																							com.ibm.wala.cast.java.ssa.AstJavaInvokeInstruction
}

de.upb.soot.basic.controlStatements.ControlStatements.gotoStmt()V{
conditional branch(eq, to iindex=-1) 3,4	conditional branch(eq, to iindex=-1) v3,v4
																							com.ibm.wala.ssa.SSAConditionalBranchInstruction
conditional branch(eq, to iindex=3) 5,4	conditional branch(eq, to iindex=3) v5,v4
																							com.ibm.wala.ssa.SSAConditionalBranchInstruction
goto (from iindex= 2 to iindex = 3)	goto (from iindex= 2 to iindex = 3)
																							com.ibm.wala.ssa.SSAGotoInstruction
goto (from iindex= 3 to iindex = 0)	goto (from iindex= 3 to iindex = 0)
																							com.ibm.wala.ssa.SSAGotoInstruction
}

de.upb.soot.basic.controlStatements.ControlStatements.simpleFor(II)V{
	v5 := v4
																							com.ibm.wala.cast.ir.ssa.AssignInstruction
6 = binaryop(lt) 8 , 2	v6 = binaryop(lt) v5 , v2
																							com.ibm.wala.classLoader.JavaLanguage$JavaInstructionFactory$4
conditional branch(eq, to iindex=-1) 6,4